AUTHORS
LICENSE
MANIFEST.in
README.rst
setup.py
calendar_sms/__init__.py
calendar_sms/admin.py
calendar_sms/forms.py
calendar_sms/models.py
calendar_sms/sms.py
calendar_sms/tasks.py
calendar_sms/test_cases.py
calendar_sms/test_settings.py
django_calendar_sms.egg-info/PKG-INFO
django_calendar_sms.egg-info/SOURCES.txt
django_calendar_sms.egg-info/dependency_links.txt
django_calendar_sms.egg-info/not-zip-safe
django_calendar_sms.egg-info/requires.txt
django_calendar_sms.egg-info/top_level.txt
requirements/package.txt
requirements/tests.txt