Metadata-Version: 1.1
Name: django-calendar-sms
Version: 2.2
Summary: This reusable Django app can help you to send sms via Google Calendar.
Home-page: http://github.com/gotlium/django-calendar-sms
Author: GoTLiuM InSPiRiT
Author-email: gotlium@gmail.com
License: UNKNOWN
Keywords: django sms
Platform: UNKNOWN
Classifier: Development Status :: 5 - Production/Stable
Classifier: Environment :: Web Environment
Classifier: Framework :: Django
Classifier: Intended Audience :: Developers
Classifier: License :: OSI Approved :: GNU General Public License (GPL)
Classifier: Operating System :: OS Independent
Classifier: Programming Language :: Python
